{
 "simulation": {
  "ID": "LS3",
  "datatype": 2,
  "simulation": true,
  "benchmark": true,
  "fastmode": true,
  "filename": "fielddata_1Hb.csv",
  "filepath": "C:/Users/paco/0_TFG/csenergy/fielddata_files/"
 },
 "model": {
  "name": "Barbero4thOrder",
  "max_err_t": 1.0,
  "max_err_tro": 1.0,
  "max_err_pr": 0.01
 },
 "site": {
  "name": "Alc\u00e1zar de San Juan",
  "latitude": 39.1,
  "longitude": -3.16,
  "altitude": 645.0
 },
 "loop": {
  "scas": 4,
  "hces": 24,
  "rated_tin": 563.15,
  "rated_tout": 666.15,
  "rated_pin": 2000000.0,
  "rated_pout": 1600000.0,
  "tmin": 288.0,
  "tmax": 670.0,
  "rated_massflow": 4.0,
  "min_massflow": 1.0,
  "row_spacing": 16.25,
  "Tracking Type": 1
 },
 "SCA": {
  "Name": "Luz LS-3",
  "SCA Length": 100.0,
  "Aperture": 5.75,
  "Focal Len": 2.1,
  "IAM Coefficient F0": 1.0,
  "IAM Coefficient F1": 0.0506,
  "IAM Coefficient F2": -0.1763,
  "Track Twist": 0.935,
  "Geom.Accuracy": 0.98,
  "Reflectance": 0.99,
  "Cleanliness": 0.97,
  "Dust": 0.98,
  "Factor": 1.0,
  "Availability": 0.99
 },
 "HCE": {
  "Name": "Solel UVAC 3",
  "Length": 4.05,
  "Absorber tube inner diameter": 0.066,
  "Absorber tube outer diameter": 0.07,
  "Glass envelope inner diameter": 0.115,
  "Glass envelope outer diameter": 0.121,
  "Min Reynolds": 30000.0,
  "Inner surface roughness": 4.5e-05,
  "Envelope transmittance": 0.96,
  "absorptance": 0.96,
  "coating": "",
  "annulus": "",
  "Absorber emittance factor A0": 0.043,
  "Absorber emittance factor A1": 0.000206,
  "Absorber absorptance": 0.96,
  "Brackets": 4.05
 },
 "HTF": {
  "source": "table",
  "name": "DOWTHERM A",
  "cp": [
   -2364.0,
   39.46,
   -0.1703,
   0.0003904,
   -4.422e-07,
   1.979e-10
  ],
  "rho": [
   1493.0,
   -3.332,
   0.01248,
   -2.968e-05,
   3.444e-08,
   -1.622e-11
  ],
  "kt": [
   0.1856,
   -0.00016,
   5.913e-12,
   0.0,
   0.0,
   0.0
  ],
  "h": [
   -651100.0,
   4121.0,
   -12.35,
   0.02771,
   -2.777e-05,
   1.106e-08
  ],
  "t": [
   285.344,
   0.000620726,
   -1.82158e-10,
   -1.42322e-16,
   3.31588e-22,
   -1.75256e-28
  ],
  "mu": [
   0.34013,
   -0.00337267,
   1.33042e-05,
   -2.60139e-08,
   2.51799e-11,
   -9.6475e-15
  ],
  "tmax": 670.0,
  "tmin": 288.0
 },
 "subfields": [
  {
   "name": "NO",
   "loops": 30
  },
  {
   "name": "NE",
   "loops": 30
  },
  {
   "name": "SO",
   "loops": 30
  },
  {
   "name": "SE",
   "loops": 30
  }
 ],
 "tags": {
  "SB.NO.a.pout": "1310-PT-1802",
  "SB.NE.a.mf": "1310-FX-1801",
  "SB.NE.a.tin": "1310-TT-1801",
  "SB.NE.a.tout": "1310-TT-1803",
  "SB.NE.a.pin": "1310-PT-1801",
  "SB.NE.a.pout": "1310-PT-1803",
  "SB.SO.a.mf": "1310-FX-1809",
  "SB.SO.a.tin": "1310-TT-1809",
  "SB.SO.a.tout": "1310-TT-1807",
  "SB.SO.a.pin": "1310-PT-1809",
  "SB.SO.a.pout": "1310-PT-1807",
  "SB.SE.a.mf": "1310-FX-1810",
  "SB.SE.a.tin": "1310-TT-1810",
  "SB.SE.a.tout": "1310-TT-1808",
  "SB.SE.a.pin": "1310-PT-1810",
  "SB.SE.a.pout": "1310-PT-1808",
  "DNI": "1300-AXT-1877R",
  "Wspd": "1300-AXT-1871R",
  "Wdir": "1300-AXT-1872R",
  "DryBulb": "1300-AXT-1873R",
  "Pressure": "1300-AXT-1883R",
  "SB.NO.a.mf": "1310-FX-1800",
  "SB.NO.a.tin": "1310-TT-1800",
  "SB.NO.a.tout": "1310-TT-1802",
  "SB.NO.a.pin": "1310-PT-1800"
 }
}